flake8_dashboard/__init__.py
flake8_dashboard/code_description.json
flake8_dashboard/plugin.py
flake8_dashboard/utils.py
flake8_dashboard/templates/index.html
flake8_dashboard/templates/assets/css/bootstrap.min.css
flake8_dashboard/templates/assets/css/light-bootstrap-dashboard.css
flake8_dashboard/templates/assets/img/CheckFailed.svg
flake8_dashboard/templates/assets/img/CheckPassed.svg
flake8_dashboard/templates/assets/img/Readme
flake8_dashboard/templates/assets/js/light-bootstrap-dashboard.js
flake8_dashboard/templates/assets/js/plotly-latest.min.js
flake8_dashboard/templates/assets/js/core/bootstrap.min.js
flake8_dashboard/templates/assets/js/core/jquery.3.2.1.min.js
flake8_dashboard/templates/assets/js/core/popper.min.js
flake8_dashboard/tests/__init__.py
flake8_dashboard/tests/test_path_handling.py
flake8_dashboard-0.1.3.dist-info/LICENSE
flake8_dashboard-0.1.3.dist-info/METADATA
flake8_dashboard-0.1.3.dist-info/WHEEL
flake8_dashboard-0.1.3.dist-info/entry_points.txt
flake8_dashboard-0.1.3.dist-info/top_level.txt
flake8_dashboard-0.1.3.dist-info/RECORD
