Metadata-Version: 2.1
Name: flake8-dashboard
Version: 0.1.3
Summary: Generate different reports of flake8 violations
Home-page: https://aperezhortal.github.io/flake8-dashboard/
Author: Andres Perez Hortal
License: Apache Software License 2.0
Keywords: flake8 dashboard html
Platform: UNKNOWN
Classifier: Framework :: Flake8
Classifier: Intended Audience :: Developers
Classifier: License :: OSI Approved :: Apache Software License
Classifier: Natural Language :: English
Classifier: Programming Language :: Python :: 3
Classifier: Programming Language :: Python :: 3.6
Classifier: Programming Language :: Python :: 3.7
Requires-Python: >=3.6
Requires-Dist: setuptools
Requires-Dist: plotly
Requires-Dist: beautifulsoup4
Requires-Dist: jsmin
Requires-Dist: jinja2
Requires-Dist: pip (>=9.0.1)
Requires-Dist: bump2version
Requires-Dist: wheel (==0.29.0)
Requires-Dist: tox (>=2.6.0)
Requires-Dist: requests
Requires-Dist: pandas
Requires-Dist: flake8
Requires-Dist: astroid (>=2.2.5)
